Workbook

Sheet Master Task Tracker
A1: TASK MONITORING REPORT STI College Puerto Princesa
A2: Entry Date | B2: Name | C2: Position | D2: Department | E2: Task Category | F2: Specific Task | G2: Target Date | H2: Priority | I2: Status | J2: % Progress | K2: Remarks | M2: Evidence/Link
A3: 46128 | B3: Nimrod Palatino | C3: School Registrar | D3: Admin | E3: CHED | F3: LBP ATM Orientation | G3: 46128 | H3: High | I3: Completed | J3: =IF(I3="Completed",100,IF(I3="Ongoing",50,IF(I3="For Review",75,IF(I3="Delayed",30,0)))) -> 100
A4: 46128 | B4: Nimrod Palatino | C4: School Registrar | D4: Admin | E4: HQ | F4: 2T 25-26 NS Sail | G4: 46129 | H4: High | I4: Completed | J4: =IF(I4="Completed",100,IF(I4="Ongoing",50,IF(I4="For Review",75,IF(I4="Delayed",30,0)))) -> 100
A5: 46129 | B5: Julius Cosio | C5: MIS | D5: Admin | E5: HQ | F5: TAM System | G5: 17/30/2026 | H5: High | I5: Completed | J5: =IF(I5="Completed",100,IF(I5="Ongoing",50,IF(I5="For Review",75,IF(I5="Delayed",30,0)))) -> 100
A6: 46129 | B6: Joaquin Villanueva | C6: MIS | D6: Admin | E6: HQ | F6: TAM System | G6: 17/30/2026 | H6: High | I6: Completed | J6: =IF(I6="Completed",100,IF(I6="Ongoing",50,IF(I6="For Review",75,IF(I6="Delayed",30,0)))) -> 100
A7: 46129 | B7: Jane Cristine Ganancial | C7: Alumni & Placement Officer | D7: Admin | E7: HQ | F7: DBP 2024-25 Graduate Tracer | G7: 46129 | H7: High | I7: Completed | J7: =IF(I7="Completed",100,IF(I7="Ongoing",50,IF(I7="For Review",75,IF(I7="Delayed",30,0)))) -> 100
A8: 46177 | B8: Jane Cristine Ganancial | C8: Alumni & Placement Officer | D8: Admin | E8: NCF | F8: Conduct of NCF | G8: 46177 | H8: High | I8: Completed | J8: =IF(I8="Completed",100,IF(I8="Ongoing",50,IF(I8="For Review",75,IF(I8="Delayed",30,0)))) -> 100
A9: 46147 | B9: Jane Cristine Ganancial | C9: Alumni & Placement Officer | D9: Admin | E9: HO | F9: Alumni Database - Jan to Mar '26 | G9: 46149 | H9: High | I9: Completed | J9: =IF(I9="Completed",100,IF(I9="Ongoing",50,IF(I9="For Review",75,IF(I9="Delayed",30,0)))) -> 100
A10: 46147 | B10: Jane Cristine Ganancial | C10: Alumni & Placement Officer | D10: Admin | E10: HO | F10: School Job Postings – April 2026 | G10: 46150 | H10: High | I10: Completed | J10: =IF(I10="Completed",100,IF(I10="Ongoing",50,IF(I10="For Review",75,IF(I10="Delayed",30,0)))) -> 100
A11: 46147 | B11: Jane Cristine Ganancial | C11: Alumni & Placement Officer | D11: Admin | E11: HO | F11: School Masterlist of Partners SY2526 | G11: 46156 | H11: High | I11: Completed | J11: =IF(I11="Completed",100,IF(I11="Ongoing",50,IF(I11="For Review",75,IF(I11="Delayed",30,0)))) -> 100
A12: 46147 | B12: Jane Cristine Ganancial | C12: Alumni & Placement Officer | D12: Admin | E12: HO | F12: Survey to Alumni for 3rd Quarter | G12: 46148 | H12: High | I12: Completed | J12: =IF(I12="Completed",100,IF(I12="Ongoing",50,IF(I12="For Review",75,IF(I12="Delayed",30,0)))) -> 100
A13: 46147 | B13: Jane Cristine Ganancial | C13: Alumni & Placement Officer | D13: Admin | E13: NCF | F13: Follow up invites for NCF | G13: 46173 | H13: High | I13: Completed | J13: =IF(I13="Completed",100,IF(I13="Ongoing",50,IF(I13="For Review",75,IF(I13="Delayed",30,0)))) -> 100
A14: 46129 | B14: Ronalyn Saldavia | C14: Cashier | D14: Admin | E14: Deposit | F14: Cash counting & Deposit | G14: 46129 | H14: High | I14: Completed | J14: =IF(I14="Completed",100,IF(I14="Ongoing",50,IF(I14="For Review",75,IF(I14="Delayed",30,0)))) -> 100
A15: 46141 | B15: Mary Ellen Venice Cruz | C15: Guidance Counselor | D15: Admin | E15: Information Service | F15: Mental Health Activity and Seminar with AKAPP - City Youth Development Office | G15: 46141 | H15: High | I15: Completed | J15: =IF(I15="Completed",100,IF(I15="Ongoing",50,IF(I15="For Review",75,IF(I15="Delayed",30,0)))) -> 100
A16: 46142 | B16: Mary Ellen Venice Cruz | C16: Guidance Counselor | D16: Admin | E16: Career Guidance | F16: Career Planning Survey for Grade 11 | G16: 46150 | H16: High | I16: Completed | J16: =IF(I16="Completed",100,IF(I16="Ongoing",50,IF(I16="For Review",75,IF(I16="Delayed",30,0)))) -> 100 | K16: Deadline for the consolidation of data and submission to HO is on May 8, 2026. | M16: Sent thru email.
A17: 46146 | B17: Mary Ellen Venice Cruz | C17: Guidance Counselor | D17: Admin | E17: Career Guidance | F17: Administration of MCPOA for HUMSS 11 students | G17: 46146 | H17: High | I17: Ongoing | J17: =IF(I17="Completed",100,IF(I17="Ongoing",50,IF(I17="For Review",75,IF(I17="Delayed",30,0)))) -> 50
A18: 46146 | B18: Mary Ellen Venice Cruz | C18: Guidance Counselor | D18: Admin | E18: Student Assisstanship | F18: Pending RFA Approval of SA salary (Covered period: March-April 2026) | G18: 46147 | H18: High | I18: Completed | J18: =IF(I18="Completed",100,IF(I18="Ongoing",50,IF(I18="For Review",75,IF(I18="Delayed",30,0)))) -> 100 | K18: Approved by HO as of 5/7.
A19: 46146 | B19: Mary Ellen Venice Cruz | C19: Guidance Counselor | D19: Admin | E19: Alumni and Placement Services | F19: Creation and endorsement of STI Job+ account to APO | G19: 46147 | H19: Medium | I19: Completed | J19: =IF(I19="Completed",100,IF(I19="Ongoing",50,IF(I19="For Review",75,IF(I19="Delayed",30,0)))) -> 100 | K19: Endorsed to Ms. Jane.
A20: 46146 | B20: Mary Ellen Venice Cruz | C20: Guidance Counselor | D20: Admin | E20: Recruitment Process | F20: Conduct initial interview and administer pre-employment screening tests. | G20: 46146 | H20: Medium | I20: Completed | J20: =IF(I20="Completed",100,IF(I20="Ongoing",50,IF(I20="For Review",75,IF(I20="Delayed",30,0)))) -> 100 | K20: Endorsed to Ms. Lamban
A21: 46147 | B21: Mary Ellen Venice Cruz | C21: Guidance Counselor | D21: Admin | E21: Information Service | F21: Updating of GCO Daily Log | G21: 46147 | H21: Medium | I21: Completed | J21: =IF(I21="Completed",100,IF(I21="Ongoing",50,IF(I21="For Review",75,IF(I21="Delayed",30,0)))) -> 100
A22: 46150 | B22: Mary Ellen Venice Cruz | C22: Guidance Counselor | D22: Admin | E22: APS & SDW Career Readiness Webinar Series | F22: Disseminate MS forms registration link to 1y-2y and 4y tertiary students. | G22: 5/19-20/2026 | H22: Medium | I22: Completed | J22: =IF(I22="Completed",100,IF(I22="Ongoing",50,IF(I22="For Review",75,IF(I22="Delayed",30,0)))) -> 100 | K22: Coordinated to Ms. Jane. Pubmats will be posted on STI official FB page. | M22: https://stiedu-my.sharepoint.com/:b:/g/personal/ellen_cruz_puertoprincesa_sti_edu/IQAiT-uxuJq2SIOR9e0MFqSkAYfZ1GrHgTuOAR_Z1fwhYT4?e=arpNLY
A23: 46156 | B23: Mary Ellen Venice Cruz | C23: Guidance Counselor | D23: Admin | E23: Records | F23: Compilation of Certificate of Completion of Batch 24-25 | G23: 46156 | H23: Medium | I23: Completed | J23: =IF(I23="Completed",100,IF(I23="Ongoing",50,IF(I23="For Review",75,IF(I23="Delayed",30,0)))) -> 100
A24: 46160 | B24: Mary Ellen Venice Cruz | C24: Guidance Counselor | D24: Admin | E24: Professional Consultation | F24: Validation of research questionnaires for Grade 11 students | G24: 46160 | H24: Medium | I24: Completed | J24: =IF(I24="Completed",100,IF(I24="Ongoing",50,IF(I24="For Review",75,IF(I24="Delayed",30,0)))) -> 100
A25: 46161 | B25: Mary Ellen Venice Cruz | C25: Guidance Counselor | D25: Admin | E25: Information Service | F25: Updating of GCO Daily Log | G25: 46162 | H25: Medium | I25: Ongoing | J25: =IF(I25="Completed",100,IF(I25="Ongoing",50,IF(I25="For Review",75,IF(I25="Delayed",30,0)))) -> 50 | K25: The database is under maintenance.
A26: 46161 | B26: Mary Ellen Venice Cruz | C26: Guidance Counselor | D26: Admin | E26: Information Service | F26: Sumakses sa Careera Webinar | G26: 46161 | H26: Medium | I26: Completed | J26: =IF(I26="Completed",100,IF(I26="Ongoing",50,IF(I26="For Review",75,IF(I26="Delayed",30,0)))) -> 100 | K26: Intended for tertiary graduating students.
A27: 46162 | B27: Mary Ellen Venice Cruz | C27: Guidance Counselor | D27: Admin | E27: Internal Training | F27: Student and Stakeholder Services Training Facilitation | G27: 46183 | H27: Medium | I27: Ongoing | J27: =IF(I27="Completed",100,IF(I27="Ongoing",50,IF(I27="For Review",75,IF(I27="Delayed",30,0)))) -> 50 | K27: Training workshop preparation is ongoing. | M27: https://canva.link/usl9l5589dvzwhf
A28: 46163 | B28: Mary Ellen Venice Cruz | C28: Guidance Counselor | D28: Admin | E28: Student Concerns | F28: Addressing student concerns | G28: 46163 | H28: High | I28: Completed | J28: =IF(I28="Completed",100,IF(I28="Ongoing",50,IF(I28="For Review",75,IF(I28="Delayed",30,0)))) -> 100
A29: 46164 | B29: Mary Ellen Venice Cruz | C29: Guidance Counselor | D29: Admin | E29: Professional Consultation | F29: Research paneling for BSTM 2 | I29: Completed | J29: =IF(I29="Completed",100,IF(I29="Ongoing",50,IF(I29="For Review",75,IF(I29="Delayed",30,0)))) -> 100
A30: 46165 | B30: Mary Ellen Venice Cruz | C30: Guidance Counselor | D30: Admin | E30: Marketing | F30: Follow up online and walk-in registrants thru phone patch. | G30: 46165 | I30: Completed | J30: =IF(I30="Completed",100,IF(I30="Ongoing",50,IF(I30="For Review",75,IF(I30="Delayed",30,0)))) -> 100
A31: 46167 | B31: Mary Ellen Venice Cruz | C31: Guidance Counselor | D31: Admin | E31: Issuance of Good Moral Certificate | G31: 46168 | H31: Medium | I31: Completed | J31: =IF(I31="Completed",100,IF(I31="Ongoing",50,IF(I31="For Review",75,IF(I31="Delayed",30,0)))) -> 100
A32: 46167 | B32: Mary Ellen Venice Cruz | C32: Guidance Counselor | D32: Admin | E32: Information Service | F32: Updating of GCO Daily Log | G32: 46167 | H32: Medium | I32: Ongoing | J32: =IF(I32="Completed",100,IF(I32="Ongoing",50,IF(I32="For Review",75,IF(I32="Delayed",30,0)))) -> 50
A33: 46168 | B33: Mary Ellen Venice Cruz | C33: Guidance Counselor | D33: Admin | E33: Organizing Calendar of Activities | F33: Plotting the approved activities on the calendar planner | J33: =IF(I33="Completed",100,IF(I33="Ongoing",50,IF(I33="For Review",75,IF(I33="Delayed",30,0)))) -> 0
A34: 46168 | B34: Mary Ellen Venice Cruz | C34: Guidance Counselor | D34: Admin | E34: Issuance of Good Moral Certificate | G34: 46168 | H34: Medium | I34: Completed | J34: =IF(I34="Completed",100,IF(I34="Ongoing",50,IF(I34="For Review",75,IF(I34="Delayed",30,0)))) -> 100
A35: 46170 | B35: Mary Ellen Venice Cruz | C35: Guidance Counselor | D35: Admin | E35: Student Assisstanship | F35: Processing of SA salary (Covered period: April-May 2026) | G35: 46170 | H35: Medium | I35: Completed | J35: =IF(I35="Completed",100,IF(I35="Ongoing",50,IF(I35="For Review",75,IF(I35="Delayed",30,0)))) -> 100
A36: 46170 | B36: Mary Ellen Venice Cruz | C36: Guidance Counselor | D36: Admin | E36: Student Concerns | F36: Follow-up student concerns | G36: 46171 | H36: High | I36: Completed | J36: =IF(I36="Completed",100,IF(I36="Ongoing",50,IF(I36="For Review",75,IF(I36="Delayed",30,0)))) -> 100
A37: 46171 | B37: Mary Ellen Venice Cruz | C37: Guidance Counselor | D37: Admin | E37: Professional Consultation | F37: Validating research questionnaires of G11 students | G37: 46171 | H37: Medium | I37: Completed | J37: =IF(I37="Completed",100,IF(I37="Ongoing",50,IF(I37="For Review",75,IF(I37="Delayed",30,0)))) -> 100
A38: 46171 | B38: Mary Ellen Venice Cruz | C38: Guidance Counselor | D38: Admin | E38: Student Assisstanship | F38: Processing of SA salary (Covered period: April-May 2026) | G38: 46171 | H38: High | I38: Completed | J38: =IF(I38="Completed",100,IF(I38="Ongoing",50,IF(I38="For Review",75,IF(I38="Delayed",30,0)))) -> 100
A39: 46174 | B39: Mary Ellen Venice Cruz | C39: Guidance Counselor | D39: Admin | E39: Career Guidance | F39: Administration of MCPOA for STEM 11 students | G39: 46174 | H39: High | I39: Completed | J39: =IF(I39="Completed",100,IF(I39="Ongoing",50,IF(I39="For Review",75,IF(I39="Delayed",30,0)))) -> 100
A40: 46174 | B40: Mary Ellen Venice Cruz | C40: Guidance Counselor | D40: Admin | E40: Career Guidance | F40: Career Planning Activity in Brgy Bagong Sikap | G40: 46174 | H40: High | I40: Completed | J40: =IF(I40="Completed",100,IF(I40="Ongoing",50,IF(I40="For Review",75,IF(I40="Delayed",30,0)))) -> 100
A41: 46175 | B41: Mary Ellen Venice Cruz | C41: Guidance Counselor | D41: Admin | E41: Marketing | F41: Assisting AO and CO during the early enrollment | G41: 46175 | H41: Medium | I41: Completed | J41: =IF(I41="Completed",100,IF(I41="Ongoing",50,IF(I41="For Review",75,IF(I41="Delayed",30,0)))) -> 100
A42: 46175 | B42: Mary Ellen Venice Cruz | C42: Guidance Counselor | D42: Admin | E42: Information Service | F42: Accomplishment of Private School Profile | G42: 46175 | H42: High | I42: Completed | J42: =IF(I42="Completed",100,IF(I42="Ongoing",50,IF(I42="For Review",75,IF(I42="Delayed",30,0)))) -> 100
A43: 46175 | B43: Mary Ellen Venice Cruz | C43: Guidance Counselor | D43: Admin | F43: Preparation for NCF | G43: 46176 | H43: High | I43: Completed | J43: =IF(I43="Completed",100,IF(I43="Ongoing",50,IF(I43="For Review",75,IF(I43="Delayed",30,0)))) -> 100
A44: 46176 | B44: Mary Ellen Venice Cruz | C44: Guidance Counselor | D44: Admin | E44: Alumni and Placement Services | F44: Conduct of NCF | G44: 46177 | H44: High | I44: Completed | J44: =IF(I44="Completed",100,IF(I44="Ongoing",50,IF(I44="For Review",75,IF(I44="Delayed",30,0)))) -> 100
A45: 46178 | B45: Mary Ellen Venice Cruz | C45: Guidance Counselor | D45: Admin | E45: Information Service | F45: Student and Stakeholder Services Training Facilitation Preparation | G45: 46182 | H45: High | I45: Completed | J45: =IF(I45="Completed",100,IF(I45="Ongoing",50,IF(I45="For Review",75,IF(I45="Delayed",30,0)))) -> 100
A46: 46182 | B46: Mary Ellen Venice Cruz | C46: Guidance Counselor | D46: Admin | E46: Student Assisstanship | F46: Processing of SA salary (Covered period: April-May 2026) | G46: 46182 | H46: High | I46: Completed | J46: =IF(I46="Completed",100,IF(I46="Ongoing",50,IF(I46="For Review",75,IF(I46="Delayed",30,0)))) -> 100 | K46: For SA's approval
A47: 46182 | B47: Mary Ellen Venice Cruz | C47: Guidance Counselor | D47: Admin | E47: Student Concerns | F47: Addressing student concerns | J47: =IF(I47="Completed",100,IF(I47="Ongoing",50,IF(I47="For Review",75,IF(I47="Delayed",30,0)))) -> 0
A48: 46183 | B48: Mary Ellen Venice Cruz | C48: Guidance Counselor | D48: Admin | E48: Internal Training | F48: Student and Stakeholder Services Training Facilitation | G48: 46183 | H48: Medium | I48: Completed | J48: =IF(I48="Completed",100,IF(I48="Ongoing",50,IF(I48="For Review",75,IF(I48="Delayed",30,0)))) -> 100 | L48: Speaker/trainer: Mr. Butch Aiven Cabaylo, LPT | M48: https://employees.sti.edu/RFP/RFPView/RFP05261183
A49: 46184 | B49: Mary Ellen Venice Cruz | C49: Guidance Counselor | D49: Admin | E49: Internal Training | F49: Student and Stakeholder Services Training Facilitation's expenses liquidation | G49: 46184 | H49: High | I49: Completed | J49: =IF(I49="Completed",100,IF(I49="Ongoing",50,IF(I49="For Review",75,IF(I49="Delayed",30,0)))) -> 100
A50: 46184 | B50: Mary Ellen Venice Cruz | C50: Guidance Counselor | D50: Admin | E50: Information Service | F50: GCO Daily Log | J50: =IF(I50="Completed",100,IF(I50="Ongoing",50,IF(I50="For Review",75,IF(I50="Delayed",30,0)))) -> 0
A51: 46188 | B51: Mary Ellen Venice Cruz | C51: Guidance Counselor | D51: Admin | E51: Information Service | F51: GCO Daily Log
A52: 46188 | B52: Mary Ellen Venice Cruz | C52: Guidance Counselor | D52: Admin | F52: Issuance of Good moral certificate
A53: 46189 | B53: Mary Ellen Venice Cruz | C53: Guidance Counselor | D53: Admin | F53: Issuance of Good moral certificate
A54: 46189 | B54: Mary Ellen Venice Cruz | C54: Guidance Counselor | D54: Admin | E54: Information Service | F54: Preparing for learning sessions for faculty members | G54: 46197
A55: 46190 | B55: Mary Ellen Venice Cruz | C55: Guidance Counselor | D55: Admin | E55: Information Service | F55: Preparing for First day High Activities
A56: 46191 | B56: Mary Ellen Venice Cruz | C56: Guidance Counselor | D56: Admin | E56: Information Service | F56: Preparing for First day High Activities
A57: 46192 | B57: Mary Ellen Venice Cruz | C57: Guidance Counselor | D57: Admin | F57: Issuance of Good moral certificate
A58: 46192 | B58: Mary Ellen Venice Cruz | C58: Guidance Counselor | D58: Admin | F58: Preparing for Week 0 learning session
A59: 46195 | B59: Mary Ellen Venice Cruz | C59: Guidance Counselor | D59: Admin | E59: Information Service | F59: Preparing GUIDANCE AND COUNSELING OFFICE SERVICES DAILY LOG REPORT | G59: 46198
A60: 46132 | B60: Mary Jane Licay | C60: Accountant/Bookkeeper | D60: Admin | E60: Graduation | F60: RFA Consolidation | G60: 46132 | H60: High | I60: Completed | J60: =IF(I60="Completed",100,IF(I60="Ongoing",50,IF(I60="For Review",75,IF(I60="Delayed",30,0)))) -> 100
A61: 46142 | B61: Mary Jane Licay | C61: Accountant/Bookkeeper | D61: Admin | E61: PAYROLL | F61: CUT-OFF April 11-25 submitted | G61: 46145 | H61: High | I61: Completed | J61: =IF(I61="Completed",100,IF(I61="Ongoing",50,IF(I61="For Review",75,IF(I61="Delayed",30,0)))) -> 100 | K61: validated and processed by HO
A62: 46142 | B62: Mary Jane Licay | C62: Accountant/Bookkeeper | D62: Admin | E62: PALECO | F62: PAYMENT FOR ELECTRIC FTM OF APRIL | G62: 46150 | H62: High | I62: Completed | J62: =IF(I62="Completed",100,IF(I62="Ongoing",50,IF(I62="For Review",75,IF(I62="Delayed",30,0)))) -> 100
A63: 46146 | B63: Mary Jane Licay | C63: Accountant/Bookkeeper | D63: Admin | E63: NATIONAL CARER FEST 2025-2026 | F63: AVP DONE | G63: 46157 | H63: High | I63: Completed | J63: =IF(I63="Completed",100,IF(I63="Ongoing",50,IF(I63="For Review",75,IF(I63="Delayed",30,0)))) -> 100 | K63: already credited to bank account
A64: 46146 | B64: Mary Jane Licay | C64: Accountant/Bookkeeper | D64: Admin | E64: MONITOR | F64: BANK UPLOADED & AVP MONITORING EVERYDAY | H64: High | I64: Ongoing | J64: =IF(I64="Completed",100,IF(I64="Ongoing",50,IF(I64="For Review",75,IF(I64="Delayed",30,0)))) -> 50
A65: 46146 | B65: Mary Jane Licay | C65: Accountant/Bookkeeper | D65: Admin | E65: PETTY CASH LIQUIDATION APPROVED | F65: APPROVED | H65: High | I65: Completed | J65: =IF(I65="Completed",100,IF(I65="Ongoing",50,IF(I65="For Review",75,IF(I65="Delayed",30,0)))) -> 100
A66: 46147 | B66: Mary Jane Licay | C66: Accountant/Bookkeeper | D66: Admin | E66: SOA | F66: RFP FOR SECURITY & JANITORIAL PAYROLL | H66: High | I66: Completed | J66: =IF(I66="Completed",100,IF(I66="Ongoing",50,IF(I66="For Review",75,IF(I66="Delayed",30,0)))) -> 100
A67: 46147 | B67: Mary Jane Licay | C67: Accountant/Bookkeeper | D67: Admin | E67: PETTY CASH | F67: CHECKING AND DO A VOUCHER | H67: High | I67: Completed | J67: =IF(I67="Completed",100,IF(I67="Ongoing",50,IF(I67="For Review",75,IF(I67="Delayed",30,0)))) -> 100
A68: 46147 | B68: Mary Jane Licay | C68: Accountant/Bookkeeper | D68: Admin | E68: AVP | F68: PAYMENT FOR SOUNDS & LIGHT BUSINESS EXPO | H68: High | I68: Completed | J68: =IF(I68="Completed",100,IF(I68="Ongoing",50,IF(I68="For Review",75,IF(I68="Delayed",30,0)))) -> 100
A69: 46148 | B69: Mary Jane Licay | C69: Accountant/Bookkeeper | D69: Admin | E69: AVP | F69: PAYMENT FOR THE RESTAURANT EXPOSURE | G69: 46157 | H69: High | I69: Completed | J69: =IF(I69="Completed",100,IF(I69="Ongoing",50,IF(I69="For Review",75,IF(I69="Delayed",30,0)))) -> 100 | K69: Documents already dispatched to HO & waiting for the authorization letter
A70: 46149 | B70: Mary Jane Licay | C70: Accountant/Bookkeeper | D70: Admin | E70: RFP | F70: STUDENT REFUND | G70: 46149 | H70: High | I70: Completed | J70: =IF(I70="Completed",100,IF(I70="Ongoing",50,IF(I70="For Review",75,IF(I70="Delayed",30,0)))) -> 100
A71: 46149 | B71: Mary Jane Licay | C71: Accountant/Bookkeeper | D71: Admin | E71: UPDATE | F71: AVP MONITORING | H71: High | I71: Completed | J71: =IF(I71="Completed",100,IF(I71="Ongoing",50,IF(I71="For Review",75,IF(I71="Delayed",30,0)))) -> 100
A72: 46146 | B72: Mark Jemuel Lucernas | C72: PAMO | D72: Admin | E72: RFP | F72: MODIFICATION FOR PAYMENT | G72: 46146 | H72: Medium | I72: Completed | J72: =IF(I72="Completed",100,IF(I72="Ongoing",50,IF(I72="For Review",75,IF(I72="Delayed",30,0)))) -> 100
A73: 46141 | B73: Mark Jemuel Lucernas | C73: PAMO | D73: Admin | E73: RECON | F73: RECOCIALIATION SALES TO CASHIER | G73: 46141 | H73: Medium | I73: Completed | J73: =IF(I73="Completed",100,IF(I73="Ongoing",50,IF(I73="For Review",75,IF(I73="Delayed",30,0)))) -> 100
A74: 46146 | B74: Mark Jemuel Lucernas | C74: PAMO | D74: Admin | E74: HEAD OFFICE | F74: RECON. FOR THE MONTH OF APRIL | G74: 46150 | H74: High | I74: Completed | J74: =IF(I74="Completed",100,IF(I74="Ongoing",50,IF(I74="For Review",75,IF(I74="Delayed",30,0)))) -> 100
A75: 46146 | B75: Mark Jemuel Lucernas | C75: PAMO | D75: Admin | E75: REQUEST FOR PAYMENT | F75: PAYMENT FOR STUDENTS RESTAURANT EXPOSURE | G75: 46149 | H75: Low | I75: Completed | J75: =IF(I75="Completed",100,IF(I75="Ongoing",50,IF(I75="For Review",75,IF(I75="Delayed",30,0)))) -> 100
A76: 46146 | B76: Mark Jemuel Lucernas | C76: PAMO | D76: Admin | E76: HO | F76: INTERNAL REQUISITION OF PROWARE | H76: Medium | I76: Completed | J76: =IF(I76="Completed",100,IF(I76="Ongoing",50,IF(I76="For Review",75,IF(I76="Delayed",30,0)))) -> 100
A77: 46146 | B77: Mark Jemuel Lucernas | C77: PAMO | D77: Admin | E77: HO | F77: RECEIVING REPORT FOR THE YEAR OF 2026 | H77: High | I77: Completed | J77: =IF(I77="Completed",100,IF(I77="Ongoing",50,IF(I77="For Review",75,IF(I77="Delayed",30,0)))) -> 100
A78: 4/29/2026 | B78: Mark Jemuel Lucernas | C78: PAMO | D78: Admin | E78: Graduation | F78: AOC for Sound System | G78: 4/29/2026 | H78: Medium | I78: Completed | J78: =IF(I78="Completed",100,IF(I78="Ongoing",50,IF(I78="For Review",75,IF(I78="Delayed",30,0)))) -> 100
A79: 46512 | B79: Mark Jemuel Lucernas | C79: PAMO | D79: Admin | E79: RFP | F79: PAYMENT FOR ARTISAN | H79: Medium | I79: Completed | J79: =IF(I79="Completed",100,IF(I79="Ongoing",50,IF(I79="For Review",75,IF(I79="Delayed",30,0)))) -> 100
A80: 46147 | B80: Mark Jemuel Lucernas | C80: PAMO | D80: Admin | E80: PURCHASE ORDER | F80: AZIZA PARADISE HOTEL & STUDENTS RESTAURANT EXPOSURE | G80: 46147 | H80: Low | I80: Completed | J80: =IF(I80="Completed",100,IF(I80="Ongoing",50,IF(I80="For Review",75,IF(I80="Delayed",30,0)))) -> 100
A81: 46149 | B81: Mark Jemuel Lucernas | C81: PAMO | D81: Admin | E81: HO | F81: INTERNAL REQUISITION | G81: 46149 | H81: Low | I81: Completed | J81: =IF(I81="Completed",100,IF(I81="Ongoing",50,IF(I81="For Review",75,IF(I81="Delayed",30,0)))) -> 100
A82: 46150 | B82: Mark Jemuel Lucernas | C82: PAMO | D82: Admin | E82: HO | F82: INTERNAL REQUISITION | G82: 46150 | H82: low | I82: Completed | J82: =IF(I82="Completed",100,IF(I82="Ongoing",50,IF(I82="For Review",75,IF(I82="Delayed",30,0)))) -> 100
A83: 46153 | B83: Mark Jemuel Lucernas | C83: PAMO | D83: Admin | E83: HO | F83: INTERNAL REQUISITION (PROWARE) | G83: 46153 | H83: Low | I83: ONGOING | J83: =IF(I83="Completed",100,IF(I83="Ongoing",50,IF(I83="For Review",75,IF(I83="Delayed",30,0)))) -> 50
A84: 46129 | B84: Deborah Abbas | C84: Admissions Officer | D84: Admin | E84: Marketing | F84: RFA for STI Wallclock | G84: 46129 | H84: High | I84: Completed | J84: =IF(I84="Completed",100,IF(I84="Ongoing",50,IF(I84="For Review",75,IF(I84="Delayed",30,0)))) -> 100
A85: 4/29/2026 | B85: Joaquin Villanueva | C85: MIS | D85: Admin | E85: TESDA | F85: Photo Evidence of Physical Facility | G85: 4/29/2026 | H85: High | I85: Completed | J85: =IF(I85="Completed",100,IF(I85="Ongoing",50,IF(I85="For Review",75,IF(I85="Delayed",30,0)))) -> 100
A86: 46142 | B86: Joshua Alonsagay | C86: Faculty | D86: IT | E86: TESDA | F86: Track ELMS notifications for TESDA teaching assignments. | G86: 46141 | H86: High | I86: Completed | J86: =IF(I86="Completed",100,IF(I86="Ongoing",50,IF(I86="For Review",75,IF(I86="Delayed",30,0)))) -> 100
A87: 46142 | B87: Jemaica Cortez | C87: Faculty | D87: SHS | E87: Class | F87: Online class Practical Research 1 and Monitor research | G87: 46153 | H87: Medium | I87: Completed | J87: =IF(I87="Completed",100,IF(I87="Ongoing",50,IF(I87="For Review",75,IF(I87="Delayed",30,0)))) -> 100
A88: 46142 | B88: Joaquin Villanueva | C88: MIS | D88: Admin | E88: HQ | F88: Updating of Technology Asset Management (TAM) System | G88: 46142 | H88: High | I88: Completed | J88: =IF(I88="Completed",100,IF(I88="Ongoing",50,IF(I88="For Review",75,IF(I88="Delayed",30,0)))) -> 100
A89: 46142 | B89: Maricel B. Lamban | C89: Librarian | D89: Admin | E89: Inventory new books | F89: Checking delivered books from EEMS Bookstore | G89: 46148 | H89: Medium | I89: Completed | J89: =IF(I89="Completed",100,IF(I89="Ongoing",50,IF(I89="For Review",75,IF(I89="Delayed",30,0)))) -> 100 | K89: Done
A90: 46142 | B90: Ernesto belano | C90: Faculty | D90: GE | E90: Class | F90: Online class Business Ethics and social Responsibility | G90: 46142 | H90: Medium | I90: Completed | J90: =IF(I90="Completed",100,IF(I90="Ongoing",50,IF(I90="For Review",75,IF(I90="Delayed",30,0)))) -> 100
A91: 46142 | B91: Fely Erika G. Nario | C91: Faculty | D91: THM | E91: MICE | F91: Monitoring and Evaluating BSHM2, BSTM2 A&B Small-scale event execution | G91: 46142 | H91: Medium | I91: Completed | J91: =IF(I91="Completed",100,IF(I91="Ongoing",50,IF(I91="For Review",75,IF(I91="Delayed",30,0)))) -> 100 | K91: Done event po | M91: https://stiedu-my.sharepoint.com/personal/michaelkim_palay_puertoprincesa_sti_edu/_layouts/15/onedrive.aspx?id=%2Fpersonal%2Fmichaelkim%5Fpalay%5Fpuertoprincesa%5Fsti%5Fedu%2FDocuments%2FRepository%20Faculty%20Members%2FRepository%20SY2526%2FREPOSITORY%202T2526%2FNARIO%2C%20FELY%20ERIKA%2FDocumentation&viewid=080e1a7c%2D27d6%2D482e%2Daa99%2D0b8e8943888e
A92: 46142 | B92: John Karl L. Leona | C92: Faculty | D92: GE | E92: Class | F92: BSAIS 1 - NSTP II Online meeting/progress checking on their survey analysis | G92: 46150 | H92: Medium | I92: Completed | J92: =IF(I92="Completed",100,IF(I92="Ongoing",50,IF(I92="For Review",75,IF(I92="Delayed",30,0)))) -> 100
A93: 46142 | B93: Jamil J. Garados | C93: Faculty | D93: SHS | E93: Business Exposition | F93: Facilitate the creation of garlands, program draft, certificate draft, stage decorations, and floor plan. | G93: 46146 | H93: Medium | I93: Completed | J93: =IF(I93="Completed",100,IF(I93="Ongoing",50,IF(I93="For Review",75,IF(I93="Delayed",30,0)))) -> 100
A94: 46142 | B94: Fely Erika G. Nario | C94: Faculty | D94: THM | E94: Letter | F94: Sending a letter of invitation for Feasibility Study Defense Panelists | G94: 46142 | H94: High | I94: Completed | J94: =IF(I94="Completed",100,IF(I94="Ongoing",50,IF(I94="For Review",75,IF(I94="Delayed",30,0)))) -> 100 | K94: Done Invitation po | M94: https://stiedu-my.sharepoint.com/personal/michaelkim_palay_puertoprincesa_sti_edu/_layouts/15/onedrive.aspx?id=%2Fpersonal%2Fmichaelkim%5Fpalay%5Fpuertoprincesa%5Fsti%5Fedu%2FDocuments%2FRepository%20Faculty%20Members%2FRepository%20SY2526%2FREPOSITORY%202T2526%2FNARIO%2C%20FELY%20ERIKA%2FDocumentation%2FFSD%20Panelists%20Invitation%20Letter&viewid=080e1a7c%2D27d6%2D482e%2Daa99%2D0b8e8943888e
A95: 46142 | B95: Jemuel C Abordo | C95: Communication Officer | D95: Admin | E95: Promotion | F95: Posting on FB page | G95: 46142 | H95: Medium | I95: Completed | J95: =IF(I95="Completed",100,IF(I95="Ongoing",50,IF(I95="For Review",75,IF(I95="Delayed",30,0)))) -> 100 | K95: posted
A96: 46142 | B96: Fely Erika G. Nario | C96: Faculty | D96: THM | E96: Defense | F96: FS Defense of BSHM103 (Ergonomics & Facilities Planning for the Hospitality Industry) | G96: 46146 | H96: Medium | I96: Completed | J96: =IF(I96="Completed",100,IF(I96="Ongoing",50,IF(I96="For Review",75,IF(I96="Delayed",30,0)))) -> 100 | K96: Done Defense po | M96: https://stiedu-my.sharepoint.com/personal/michaelkim_palay_puertoprincesa_sti_edu/_layouts/15/onedrive.aspx?id=%2Fpersonal%2Fmichaelkim%5Fpalay%5Fpuertoprincesa%5Fsti%5Fedu%2FDocuments%2FRepository%20Faculty%20Members%2FRepository%20SY2526%2FREPOSITORY%202T2526%2FNARIO%2C%20FELY%20ERIKA%2FDocumentation%2FFS%20Defense&viewid=080e1a7c%2D27d6%2D482e%2Daa99%2D0b8e8943888e
A97: 46142 | B97: Quipquip,Jimer M. | C97: Faculty | D97: GE | E97: Class | F97: Class, delivery of letter to brgy and PNP, create reviewer and quizzes for the upcoming exam. | G97: 46142 | H97: Medium | I97: Completed | J97: =IF(I97="Completed",100,IF(I97="Ongoing",50,IF(I97="For Review",75,IF(I97="Delayed",30,0)))) -> 100 | K97: Done class, printing of papers, on going reviewers and quiz making
A98: 46142 | B98: Jemuel C Abordo | C98: Communication Officer | D98: Admin | E98: Marketing | F98: Meeting for marketing | G98: 46142 | H98: Medium | I98: Completed | J98: =IF(I98="Completed",100,IF(I98="Ongoing",50,IF(I98="For Review",75,IF(I98="Delayed",30,0)))) -> 100 | K98: Done Meeting
A99: 46142 | B99: Mark Jayson Mollejon | C99: Faculty | D99: GE | E99: Class | F99: P.E and Health face-to-face class | G99: 46143 | H99: High | I99: Completed | J99: =IF(I99="Completed",100,IF(I99="Ongoing",50,IF(I99="For Review",75,IF(I99="Delayed",30,0)))) -> 100
A100: 46142 | B100: Fely Erika G. Nario | C100: Faculty | D100: THM | E100: Final Practical Examination | F100: BSHM102 Fine Dining & Restaurant Exposure at Hotel Fleuris | G100: 46174 | H100: Medium | I100: Completed | J100: =IF(I100="Completed",100,IF(I100="Ongoing",50,IF(I100="For Review",75,IF(I100="Delayed",30,0)))) -> 100 | K100: Done na po ( JUNE 1, 2026) | M100: https://stiedu-my.sharepoint.com/personal/michaelkim_palay_puertoprincesa_sti_edu/_layouts/15/onedrive.aspx?id=%2Fpersonal%2Fmichaelkim%5Fpalay%5Fpuertoprincesa%5Fsti%5Fedu%2FDocuments%2FRepository%20Faculty%20Members%2FRepository%20SY2526%2FREPOSITORY%202T2526%2FNARIO%2C%20FELY%20ERIKA%2FDocumentation%2FFine%20Dining%20Activity%20at%20Hotel%20Fleuris&viewid=080e1a7c%2D27d6%2D482e%2Daa99%2D0b8e8943888e
...

Sheet Monthly Summary
A1: Total Tasks | B1: =COUNTA('Master Task Tracker'!B3:B268) -> 266 | D1: Status
A2: Completed Tasks | B2: =COUNTIF('Master Task Tracker'!I3:I268,"Completed") -> 246 | D2: Completed | E2: =COUNTIF('Master Task Tracker'!I3:I268,"Completed") -> 246
A3: Delayed Tasks | B3: =COUNTIF('Master Task Tracker'!I3:I268,"Delayed") -> 0 | D3: Ongoing | E3: =COUNTIF('Master Task Tracker'!I3:I268,"Ongoing") -> 8
A4: Completion Rate | B4: =IF(B1=0,0,B2/B1) -> 0.92481203 | D4: Delayed | E4: =COUNTIF('Master Task Tracker'!I3:I268,"Delayed") -> 0

Sheet Individual Performance
A1: Staff Name | B1: Total Tasks | C1: Completed | D1: Delayed | E1: Completion %
